setup.py
read_dicom/__init__.py
read_dicom.egg-info/PKG-INFO
read_dicom.egg-info/SOURCES.txt
read_dicom.egg-info/dependency_links.txt
read_dicom.egg-info/not-zip-safe
read_dicom.egg-info/top_level.txt