Metadata-Version: 1.0
Name: read-dicom
Version: 0.1
Summary: Read DICOM files in Python
Home-page: http://github.com/louismullie/read_dicom
Author: Read DICCOM files in Python
Author-email: louis.mullie@gmail.com
License: MIT
Platform: UNKNOWN
